syscli/__init__.py
syscli/cli.py
pysys_cli-0.0.2.dist-info/LICENSE
pysys_cli-0.0.2.dist-info/METADATA
pysys_cli-0.0.2.dist-info/WHEEL
pysys_cli-0.0.2.dist-info/entry_points.txt
pysys_cli-0.0.2.dist-info/top_level.txt
pysys_cli-0.0.2.dist-info/RECORD
